lazyfit/Lazyfitter.py
lazyfit/Rbf.py
lazyfit/__init__.py
lazyfit-0.1.2.dist-info/LICENSE
lazyfit-0.1.2.dist-info/METADATA
lazyfit-0.1.2.dist-info/WHEEL
lazyfit-0.1.2.dist-info/top_level.txt
lazyfit-0.1.2.dist-info/RECORD
