Metadata-Version: 2.1
Name: lazyfit
Version: 0.1.2
Summary: A python package that helps with the construction and optimization of RBF interpolants.
Home-page: https://github.com/redhorn144/lazyfit.git
Author: Alex Shaffer
Author-email: alex.shaffer144@gmail.com
License: UNKNOWN
Keywords: Interpolation,Data Science
Platform: UNKNOWN
Classifier: Programming Language :: Python :: 3
Classifier: Programming Language :: Python :: 3.6
Classifier: Programming Language :: Python :: 3.7
Classifier: Programming Language :: Python :: 3.8
Classifier: Programming Language :: Python :: 3.9
Classifier: License :: OSI Approved :: MIT License
Classifier: Intended Audience :: Developers
Classifier: Intended Audience :: Other Audience
Classifier: Intended Audience :: Science/Research
Classifier: Intended Audience :: Education
Classifier: Operating System :: Microsoft :: Windows
Classifier: Operating System :: OS Independent
Requires-Dist: numpy ~=1.23.5
Requires-Dist: scipy ~=1.10.1
